setup.py
pydler/__init__.py
pydler/__version__.py
pydler/config.py
pydler/downloader.py
pydler/main.py
pydler/run.py
pydler/server.py
pydler/tasks.py
pydler.egg-info/PKG-INFO
pydler.egg-info/SOURCES.txt
pydler.egg-info/dependency_links.txt
pydler.egg-info/entry_points.txt
pydler.egg-info/requires.txt
pydler.egg-info/top_level.txt
pydler/cli/__init__.py
pydler/cli/download.py
pydler/cli/download_m3u8.py
pydler/cli/gunicorn_config.py
pydler/cli/server.py
pydler/cli/taskadd.py
pydler/common/__init__.py
pydler/common/constants.py
pydler/common/loggers.py
pydler/downloader/__init__.py
pydler/downloader/enum.py
pydler/downloader/m3u8_downloader.py
pydler/downloader/models.py